Workbook
Name Slicer_Category: #N/A
Name Slicer_Category1: #N/A
Name Slicer_PaymentMode: #N/A
Name Slicer_PaymentMode1: #N/A
Name Slicer_State: #N/A
Name Slicer_State1: #N/A

Sheet pivot_table
A3: Category | B3: Sum of Amount | C3: Sum of Profit | E3: State | F3: Sum of Amount | G3: Sum of Quantity | I3: PaymentMode | J3: Sum of Amount | K3: Sum of Quantity
A4: Electronics | B4: 300653 | C4: 67477 | E4: California | F4: 1086436 | G4: 2319 | I4: COD | J4: 1141790 | K4: 2191 | M4: Category | N4: Sub-Category | O4: Sum of Amount | P4: Sum of Profit
A5: Furniture | B5: 416016 | C5: 115391 | E5: Florida | F5: 1091174 | G5: 2145 | I5: Credit Card | J5: 1281044 | K5: 2685 | M5: Electronics | N5: Electronic Games | O5: 565092 | P5: 148454
A6: Office Supplies | B6: 369767 | C6: 95946 | E6: Illinois | F6: 978738 | G6: 1820 | I6: Debit Card | J6: 1385546 | K6: 2773 | N6: Laptops | O6: 419950 | P6: 110260
A7: Grand Total | B7: 1086436 | C7: 278814 | E7: New York | F7: 1120559 | G7: 2479 | I7: EMI | J7: 1114297 | K7: 2371 | N7: Phones | O7: 503055 | P7: 113607
E8: Ohio | F8: 884768 | G8: 2041 | I8: UPI | J8: 1250473 | K8: 2725 | N8: Printers | O8: 566359 | P8: 146259
E9: Texas | F9: 1011475 | G9: 1941 | I9: Grand Total | J9: 6173150 | K9: 12745 | M9: Electronics Total | O9: 2054456 | P9: 518580
A10: Year-Month | B10: Sum of Amount | C10: Sum of Quantity | E10: Grand Total | F10: 6173150 | G10: 12745 | M10: Furniture | N10: Bookcases | O10: 413165 | P10: 118000
A11: 2020-03 | B11: 11179 | C11: 20 | N11: Chairs | O11: 431964 | P11: 122892
A12: 2020-04 | B12: 84897 | C12: 154 | N12: Sofas | O12: 568367 | P12: 142854
A13: 2020-05 | B13: 78360 | C13: 165 | N13: Tables | O13: 615688 | P13: 156796
A14: 2020-06 | B14: 32121 | C14: 72 | M14: Furniture Total | O14: 2029184 | P14: 540542
A15: 2020-07 | B15: 31710 | C15: 50 | M15: Office Supplies | N15: Binders | O15: 384611 | P15: 97257
A16: 2020-08 | B16: 68029 | C16: 75 | N16: Markers | O16: 627875 | P16: 174749
A17: 2020-09 | B17: 66394 | C17: 147 | N17: Paper | O17: 524755 | P17: 149723
A18: 2020-10 | B18: 82798 | C18: 197 | N18: Pens | O18: 552269 | P18: 129846
A19: 2020-11 | B19: 86010 | C19: 194 | M19: Office Supplies Total | O19: 2089510 | P19: 551575
A20: 2020-12 | B20: 84725 | C20: 146 | M20: Grand Total | O20: 6173150 | P20: 1610697
A21: 2021-01 | B21: 12997 | C21: 48
A22: 2021-02 | B22: 49047 | C22: 109
A23: 2021-03 | B23: 57969 | C23: 97
A24: 2021-04 | B24: 53951 | C24: 89
A25: 2021-05 | B25: 80790 | C25: 154
A26: 2021-06 | B26: 56841 | C26: 159
A27: 2021-07 | B27: 52669 | C27: 89
A28: 2021-08 | B28: 63733 | C28: 165
A29: 2021-09 | B29: 29613 | C29: 68
A30: 2021-10 | B30: 121993 | C30: 182
A31: 2021-11 | B31: 106979 | C31: 213
A32: 2021-12 | B32: 107107 | C32: 262
... A72: Grand Total | B72: 4118694 | C72: 8487

Sheet sales_dataset
A1: ORDER ID | B1: Amount | C1: Profit | D1: Quantity | E1: Category | F1: Sub-Category | G1: PaymentMode | H1: Order Date | I1: CustomerName | J1: State | K1: City | L1: Year-Month
A2: B-25936 | B2: 9992 | C2: 3696 | D2: 20 | E2: Office Supplies | F2: Pens | G2: Debit Card | H2: 44449 | I2: Patrick Williams | J2: New York | K2: Rochester | L2: 2021-10
A3: B-25936 | B3: 9992 | C3: 3696 | D3: 20 | E3: Office Supplies | F3: Pens | G3: Debit Card | H3: 4/15/2022 | I3: Susan Burke | J3: Texas | K3: Austin | L3: 2022-04
A4: B-25936 | B4: 9992 | C4: 3696 | D4: 20 | E4: Office Supplies | F4: Pens | G4: Debit Card | H4: 8/29/2022 | I4: Brent Hernandez | J4: New York | K4: Rochester | L4: 2022-08
A5: B-25861 | B5: 9989 | C5: 3930 | D5: 14 | E5: Furniture | F5: Tables | G5: Debit Card | H5: 3/28/2022 | I5: Tammy Anthony | J5: Ohio | K5: Cleveland | L5: 2022-03
A6: B-25861 | B6: 9989 | C6: 3930 | D6: 14 | E6: Furniture | F6: Tables | G6: Debit Card | H6: 9/22/2022 | I6: Cassandra Farley | J6: Florida | K6: Orlando | L6: 2022-09
A7: B-25004 | B7: 9965 | C7: 3033 | D7: 16 | E7: Office Supplies | F7: Markers | G7: COD | H7: 6/17/2020 | I7: Jennifer Marshall | J7: California | K7: San Francisco | L7: 2020-06
A8: B-25004 | B8: 9965 | C8: 3033 | D8: 16 | E8: Office Supplies | F8: Markers | G8: COD | H8: 44935 | I8: Frank Garcia | J8: New York | K8: Buffalo | L8: 2023-09
A9: B-25945 | B9: 9952 | C9: 3301 | D9: 15 | E9: Electronics | F9: Electronic Games | G9: Debit Card | H9: 45202 | I9: Tanya Thomas MD | J9: Texas | K9: Dallas | L9: 2023-03
A10: B-26445 | B10: 9921 | C10: 1451 | D10: 15 | E10: Furniture | F10: Sofas | G10: EMI | H10: 44534 | I10: Christopher Rogers | J10: Illinois | K10: Chicago | L10: 2021-04
A11: B-25809 | B11: 9916 | C11: 4602 | D11: 14 | E11: Furniture | F11: Chairs | G11: UPI | H11: 44776 | I11: Kelly Smith | J11: Ohio | K11: Cleveland | L11: 2022-03
A12: B-25809 | B12: 9916 | C12: 4602 | D12: 14 | E12: Furniture | F12: Chairs | G12: UPI | H12: 44785 | I12: Sabrina Hartman | J12: Florida | K12: Tampa | L12: 2022-12
A13: B-25441 | B13: 9914 | C13: 3858 | D13: 16 | E13: Furniture | F13: Sofas | G13: Credit Card | H13: 6/24/2022 | I13: Jeffrey Weber | J13: New York | K13: Buffalo | L13: 2022-06
A14: B-25441 | B14: 9914 | C14: 3858 | D14: 16 | E14: Furniture | F14: Sofas | G14: Credit Card | H14: 45510 | I14: Andrew Krueger | J14: New York | K14: Rochester | L14: 2024-06
A15: B-25738 | B15: 9909 | C15: 2999 | D15: 18 | E15: Office Supplies | F15: Markers | G15: COD | H15: 5/15/2021 | I15: Albert Alexander Jr. | J15: Ohio | K15: Cleveland | L15: 2021-05
A16: B-25738 | B16: 9909 | C16: 2999 | D16: 18 | E16: Office Supplies | F16: Markers | G16: COD | H16: 1/13/2022 | I16: Teresa Perez | J16: Texas | K16: Austin | L16: 2022-01
A17: B-25241 | B17: 9905 | C17: 633 | D17: 17 | E17: Office Supplies | F17: Pens | G17: EMI | H17: 7/18/2021 | I17: John Munoz | J17: Texas | K17: Dallas | L17: 2021-07
A18: B-25241 | B18: 9905 | C18: 633 | D18: 17 | E18: Office Supplies | F18: Pens | G18: EMI | H18: 44237 | I18: David Clark | J18: Florida | K18: Tampa | L18: 2021-10
A19: B-26507 | B19: 9895 | C19: 1598 | D19: 20 | E19: Furniture | F19: Bookcases | G19: COD | H19: 12/16/2023 | I19: Janet Guerrero | J19: New York | K19: Rochester | L19: 2023-12
A20: B-26508 | B20: 9894 | C20: 3698 | D20: 20 | E20: Office Supplies | F20: Paper | G20: EMI | H20: 2/25/2024 | I20: Christopher Kirk | J20: Florida | K20: Miami | L20: 2024-02
A21: B-26508 | B21: 9894 | C21: 3698 | D21: 20 | E21: Office Supplies | F21: Paper | G21: EMI | H21: 6/15/2021 | I21: Eric Stevens | J21: Florida | K21: Miami | L21: 2021-06
A22: B-25267 | B22: 9894 | C22: 829 | D22: 1 | E22: Office Supplies | F22: Binders | G22: COD | H22: 8/21/2022 | I22: Michael Bell | J22: California | K22: San Diego | L22: 2022-08
A23: B-25427 | B23: 9884 | C23: 4446 | D23: 7 | E23: Electronics | F23: Printers | G23: EMI | H23: 43925 | I23: Richard Blair | J23: Florida | K23: Miami | L23: 2020-04
A24: B-25901 | B24: 9883 | C24: 4812 | D24: 16 | E24: Office Supplies | F24: Paper | G24: UPI | H24: 10/20/2020 | I24: Jeffrey Middleton | J24: New York | K24: Buffalo | L24: 2020-10
A25: B-25901 | B25: 9883 | C25: 4812 | D25: 16 | E25: Office Supplies | F25: Paper | G25: UPI | H25: 44873 | I25: Veronica Kelley | J25: Florida | K25: Orlando | L25: 2022-08
A26: B-25901 | B26: 9883 | C26: 4812 | D26: 16 | E26: Office Supplies | F26: Paper | G26: UPI | H26: 10/17/2021 | I26: Leslie Bean | J26: Illinois | K26: Springfield | L26: 2021-10
A27: B-26357 | B27: 9879 | C27: 4930 | D27: 15 | E27: Electronics | F27: Laptops | G27: Debit Card | H27: 45144 | I27: Brandi Vasquez | J27: New York | K27: Rochester | L27: 2023-06
A28: B-25501 | B28: 9874 | C28: 3895 | D28: 4 | E28: Office Supplies | F28: Binders | G28: EMI | H28: 2/24/2025 | I28: Michelle Anderson | J28: Ohio | K28: Cleveland | L28: 2025-02
A29: B-26565 | B29: 9873 | C29: 4585 | D29: 7 | E29: Office Supplies | F29: Paper | G29: Credit Card | H29: 44112 | I29: Maria Galvan | J29: Ohio | K29: Columbus | L29: 2020-08
A30: B-26443 | B30: 9869 | C30: 4299 | D30: 12 | E30: Electronics | F30: Printers | G30: Debit Card | H30: 3/21/2023 | I30: Dale Craig | J30: California | K30: San Diego | L30: 2023-03
A31: B-26443 | B31: 9869 | C31: 4299 | D31: 12 | E31: Electronics | F31: Printers | G31: Debit Card | H31: 12/28/2023 | I31: Joseph Hooper | J31: New York | K31: Buffalo | L31: 2023-12
A32: B-25861 | B32: 9851 | C32: 2669 | D32: 19 | E32: Electronics | F32: Electronic Games | G32: Debit Card | H32: 3/28/2022 | I32: Tammy Anthony | J32: Ohio | K32: Cleveland | L32: 2022-03
A33: B-25861 | B33: 9851 | C33: 2669 | D33: 19 | E33: Electronics | F33: Electronic Games | G33: Debit Card | H33: 7/15/2023 | I33: Jennifer Chase | J33: New York | K33: Buffalo | L33: 2023-07
A34: B-25861 | B34: 9851 | C34: 2669 | D34: 19 | E34: Electronics | F34: Electronic Games | G34: Debit Card | H34: 9/22/2022 | I34: Cassandra Farley | J34: Florida | K34: Orlando | L34: 2022-09
A35: B-25044 | B35: 9849 | C35: 963 | D35: 1 | E35: Office Supplies | F35: Pens | G35: Credit Card | H35: 4/16/2024 | I35: April Welch | J35: Illinois | K35: Springfield | L35: 2024-04
A36: B-26019 | B36: 9845 | C36: 3062 | D36: 9 | E36: Office Supplies | F36: Paper | G36: COD | H36: 3/14/2025 | I36: Elizabeth Hernandez | J36: Florida | K36: Orlando | L36: 2025-03
A37: B-25198 | B37: 9840 | C37: 3870 | D37: 11 | E37: Electronics | F37: Printers | G37: Debit Card | H37: 4/25/2023 | I37: Cynthia Ferguson | J37: Texas | K37: Austin | L37: 2023-04
A38: B-26790 | B38: 9837 | C38: 384 | D38: 1 | E38: Electronics | F38: Laptops | G38: UPI | H38: 9/21/2020 | I38: Jennifer Cooke | J38: California | K38: San Francisco | L38: 2020-09
A39: B-26332 | B39: 9835 | C39: 2571 | D39: 16 | E39: Furniture | F39: Tables | G39: COD | H39: 44840 | I39: George Foster | J39: Texas | K39: Dallas | L39: 2022-06
A40: B-26332 | B40: 9835 | C40: 2571 | D40: 16 | E40: Furniture | F40: Tables | G40: COD | H40: 11/16/2021 | I40: Nicholas Anderson | J40: Florida | K40: Orlando | L40: 2021-11
A41: B-26332 | B41: 9835 | C41: 2571 | D41: 16 | E41: Furniture | F41: Tables | G41: COD | H41: 8/17/2022 | I41: Emily Ellison | J41: California | K41: Los Angeles | L41: 2022-08
A42: B-26592 | B42: 9832 | C42: 1270 | D42: 1 | E42: Office Supplies | F42: Pens | G42: COD | H42: 44752 | I42: James Hernandez | J42: California | K42: San Francisco | L42: 2022-10
A43: B-26841 | B43: 9827 | C43: 4208 | D43: 13 | E43: Furniture | F43: Chairs | G43: Debit Card | H43: 44174 | I43: Jill Jones | J43: New York | K43: New York City | L43: 2020-09
A44: B-25156 | B44: 9820 | C44: 793 | D44: 16 | E44: Furniture | F44: Chairs | G44: Credit Card | H44: 8/29/2021 | I44: Tom Lawson | J44: New York | K44: Buffalo | L44: 2021-08
A45: B-25226 | B45: 9808 | C45: 2117 | D45: 2 | E45: Office Supplies | F45: Pens | G45: UPI | H45: 4/23/2024 | I45: Nicole Warren | J45: California | K45: Los Angeles | L45: 2024-04
A46: B-26034 | B46: 9789 | C46: 2071 | D46: 18 | E46: Furniture | F46: Bookcases | G46: Debit Card | H46: 12/28/2023 | I46: Aaron Johnson | J46: New York | K46: Rochester | L46: 2023-12
A47: B-26978 | B47: 9776 | C47: 3750 | D47: 9 | E47: Office Supplies | F47: Binders | G47: UPI | H47: 45841 | I47: Roger Harris | J47: Illinois | K47: Springfield | L47: 2025-03
A48: B-25387 | B48: 9775 | C48: 4507 | D48: 5 | E48: Office Supplies | F48: Markers | G48: UPI | H48: 43989 | I48: Amy Thompson | J48: Ohio | K48: Cincinnati | L48: 2020-07
A49: B-25591 | B49: 9770 | C49: 4132 | D49: 7 | E49: Electronics | F49: Electronic Games | G49: UPI | H49: 12/25/2022 | I49: Randy Johnson | J49: Ohio | K49: Columbus | L49: 2022-12
A50: B-26293 | B50: 9768 | C50: 4518 | D50: 8 | E50: Furniture | F50: Tables | G50: Credit Card | H50: 11/26/2021 | I50: Michael Hunt | J50: Texas | K50: Dallas | L50: 2021-11
A51: B-26980 | B51: 9752 | C51: 3618 | D51: 5 | E51: Furniture | F51: Bookcases | G51: Debit Card | H51: 2/21/2024 | I51: Mary Johnson | J51: New York | K51: Rochester | L51: 2024-02
A52: B-26980 | B52: 9752 | C52: 3618 | D52: 5 | E52: Furniture | F52: Bookcases | G52: Debit Card | H52: 10/31/2022 | I52: Joseph Knight | J52: Illinois | K52: Peoria | L52: 2022-10
A53: B-26883 | B53: 9751 | C53: 2459 | D53: 13 | E53: Office Supplies | F53: Pens | G53: COD | H53: 11/23/2020 | I53: Christian Jones | J53: New York | K53: Buffalo | L53: 2020-11
A54: B-26287 | B54: 9730 | C54: 2341 | D54: 2 | E54: Furniture | F54: Chairs | G54: EMI | H54: 45329 | I54: Renee Solomon | J54: Florida | K54: Tampa | L54: 2024-07
A55: B-26776 | B55: 9726 | C55: 1275 | D55: 5 | E55: Electronics | F55: Electronic Games | G55: UPI | H55: 6/27/2023 | I55: David Padilla | J55: Florida | K55: Miami | L55: 2023-06
A56: B-26776 | B56: 9726 | C56: 1275 | D56: 5 | E56: Electronics | F56: Electronic Games | G56: UPI | H56: 12/27/2024 | I56: Connor Morgan | J56: Illinois | K56: Chicago | L56: 2024-12
A57: B-26776 | B57: 9726 | C57: 1275 | D57: 5 | E57: Electronics | F57: Electronic Games | G57: UPI | H57: 7/25/2021 | I57: Robert Stone | J57: New York | K57: Buffalo | L57: 2021-07
A58: B-25511 | B58: 9707 | C58: 3483 | D58: 10 | E58: Electronics | F58: Electronic Games | G58: EMI | H58: 1/29/2025 | I58: Samuel Hayes | J58: Illinois | K58: Peoria | L58: 2025-01
A59: B-25885 | B59: 9704 | C59: 4339 | D59: 12 | E59: Office Supplies | F59: Pens | G59: COD | H59: 44350 | I59: Dawn Howard | J59: Texas | K59: Houston | L59: 2021-03
A60: B-26724 | B60: 9694 | C60: 4361 | D60: 1 | E60: Furniture | F60: Chairs | G60: EMI | H60: 45027 | I60: Roberto Parrish | J60: Illinois | K60: Springfield | L60: 2023-11
A61: B-26332 | B61: 9691 | C61: 3056 | D61: 13 | E61: Office Supplies | F61: Markers | G61: Credit Card | H61: 44840 | I61: George Foster | J61: Texas | K61: Dallas | L61: 2022-06
A62: B-26332 | B62: 9691 | C62: 3056 | D62: 13 | E62: Office Supplies | F62: Markers | G62: Credit Card | H62: 11/16/2021 | I62: Nicholas Anderson | J62: Florida | K62: Orlando | L62: 2021-11
A63: B-26332 | B63: 9691 | C63: 3056 | D63: 13 | E63: Office Supplies | F63: Markers | G63: Credit Card | H63: 8/17/2022 | I63: Emily Ellison | J63: California | K63: Los Angeles | L63: 2022-08
A64: B-26470 | B64: 9683 | C64: 1014 | D64: 5 | E64: Electronics | F64: Printers | G64: UPI | H64: 12/27/2024 | I64: Morgan Montes | J64: California | K64: San Diego | L64: 2024-12
A65: B-26470 | B65: 9683 | C65: 1014 | D65: 5 | E65: Electronics | F65: Printers | G65: UPI | H65: 6/18/2021 | I65: Christine Mosley | J65: Ohio | K65: Cincinnati | L65: 2021-06
A66: B-26470 | B66: 9683 | C66: 1014 | D66: 5 | E66: Electronics | F66: Printers | G66: UPI | H66: 5/27/2023 | I66: Ashley Rodriguez | J66: Texas | K66: Austin | L66: 2023-05
A67: B-26470 | B67: 9683 | C67: 1014 | D67: 5 | E67: Electronics | F67: Printers | G67: UPI | H67: 44540 | I67: Elizabeth King | J67: Texas | K67: Dallas | L67: 2021-10
A68: B-26910 | B68: 9680 | C68: 3295 | D68: 9 | E68: Furniture | F68: Tables | G68: COD | H68: 4/29/2024 | I68: Mr. Ralph Garcia Jr. | J68: New York | K68: Rochester | L68: 2024-04
A69: B-26251 | B69: 9659 | C69: 2226 | D69: 16 | E69: Office Supplies | F69: Binders | G69: Debit Card | H69: 45022 | I69: Brenda Murphy | J69: California | K69: San Francisco | L69: 2023-06
A70: B-25131 | B70: 9654 | C70: 4111 | D70: 1 | E70: Office Supplies | F70: Paper | G70: UPI | H70: 6/27/2022 | I70: Timothy Murphy | J70: California | K70: San Francisco | L70: 2022-06
A71: B-25200 | B71: 9653 | C71: 2471 | D71: 6 | E71: Office Supplies | F71: Paper | G71: UPI | H71: 45511 | I71: Marissa Hartman | J71: New York | K71: Buffalo | L71: 2024-07
A72: B-25829 | B72: 9640 | C72: 2606 | D72: 2 | E72: Furniture | F72: Bookcases | G72: Credit Card | H72: 10/31/2021 | I72: Anthony Barnett | J72: Illinois | K72: Peoria | L72: 2021-10
A73: B-25936 | B73: 9619 | C73: 3420 | D73: 7 | E73: Office Supplies | F73: Binders | G73: UPI | H73: 44449 | I73: Patrick Williams | J73: New York | K73: Rochester | L73: 2021-10
A74: B-25936 | B74: 9619 | C74: 3420 | D74: 7 | E74: Office Supplies | F74: Binders | G74: UPI | H74: 4/15/2022 | I74: Susan Burke | J74: Texas | K74: Austin | L74: 2022-04
A75: B-25936 | B75: 9619 | C75: 3420 | D75: 7 | E75: Office Supplies | F75: Binders | G75: UPI | H75: 8/29/2022 | I75: Brent Hernandez | J75: New York | K75: Rochester | L75: 2022-08
A76: B-26843 | B76: 9612 | C76: 2572 | D76: 17 | E76: Office Supplies | F76: Pens | G76: Credit Card | H76: 7/31/2021 | I76: Megan Williams | J76: Texas | K76: Dallas | L76: 2021-07
A77: B-26628 | B77: 9609 | C77: 4339 | D77: 3 | E77: Furniture | F77: Sofas | G77: Debit Card | H77: 9/19/2024 | I77: George Ashley | J77: Texas | K77: Houston | L77: 2024-09
A78: B-26628 | B78: 9609 | C78: 4339 | D78: 3 | E78: Furniture | F78: Sofas | G78: Debit Card | H78: 43955 | I78: Sara Bailey | J78: Ohio | K78: Cincinnati | L78: 2020-04
A79: B-26601 | B79: 9574 | C79: 4045 | D79: 19 | E79: Furniture | F79: Bookcases | G79: UPI | H79: 3/13/2024 | I79: Melinda Montoya | J79: California | K79: San Francisco | L79: 2024-03
A80: B-25742 | B80: 9565 | C80: 1691 | D80: 3 | E80: Office Supplies | F80: Paper | G80: Debit Card | H80: 45329 | I80: Taylor White | J80: Illinois | K80: Springfield | L80: 2024-07
A81: B-25979 | B81: 9562 | C81: 325 | D81: 2 | E81: Electronics | F81: Printers | G81: Debit Card | H81: 5/13/2022 | I81: Andrew Kirby | J81: California | K81: San Diego | L81: 2022-05
A82: B-26571 | B82: 9548 | C82: 1806 | D82: 9 | E82: Electronics | F82: Printers | G82: COD | H82: 10/20/2022 | I82: Kimberly Smith | J82: Illinois | K82: Springfield | L82: 2022-10
A83: B-25884 | B83: 9538 | C83: 3158 | D83: 20 | E83: Electronics | F83: Printers | G83: Credit Card | H83: 45391 | I83: Sean Elliott | J83: California | K83: San Francisco | L83: 2024-09
A84: B-25884 | B84: 9538 | C84: 3158 | D84: 20 | E84: Electronics | F84: Printers | G84: Credit Card | H84: 5/18/2021 | I84: Wanda West | J84: Ohio | K84: Cleveland | L84: 2021-05
A85: B-26622 | B85: 9536 | C85: 1437 | D85: 9 | E85: Electronics | F85: Phones | G85: UPI | H85: 43865 | I85: Timothy Jensen | J85: Florida | K85: Orlando | L85: 2020-04
A86: B-26041 | B86: 9498 | C86: 256 | D86: 12 | E86: Electronics | F86: Phones | G86: COD | H86: 2/22/2021 | I86: Matthew James | J86: Illinois | K86: Peoria | L86: 2021-02
A87: B-26041 | B87: 9498 | C87: 256 | D87: 12 | E87: Electronics | F87: Phones | G87: COD | H87: 44357 | I87: Jerry Alvarado | J87: New York | K87: New York City | L87: 2021-10
A88: B-25703 | B88: 9438 | C88: 1801 | D88: 4 | E88: Electronics | F88: Electronic Games | G88: COD | H88: 4/19/2023 | I88: Steven Acosta | J88: Florida | K88: Orlando | L88: 2023-04
A89: B-25703 | B89: 9438 | C89: 1801 | D89: 4 | E89: Electronics | F89: Electronic Games | G89: COD | H89: 10/29/2023 | I89: Lindsay Jackson | J89: Texas | K89: Austin | L89: 2023-10
A90: B-26095 | B90: 9406 | C90: 1137 | D90: 16 | E90: Office Supplies | F90: Markers | G90: UPI | H90: 10/20/2021 | I90: Leroy Harris | J90: Texas | K90: Houston | L90: 2021-10
A91: B-26803 | B91: 9399 | C91: 1949 | D91: 12 | E91: Electronics | F91: Printers | G91: UPI | H91: 5/16/2022 | I91: Elizabeth White | J91: New York | K91: Rochester | L91: 2022-05
A92: B-26219 | B92: 9386 | C92: 2555 | D92: 20 | E92: Office Supplies | F92: Markers | G92: Credit Card | H92: 8/19/2020 | I92: Mark Padilla | J92: California | K92: San Diego | L92: 2020-08
A93: B-26219 | B93: 9386 | C93: 2555 | D93: 20 | E93: Office Supplies | F93: Markers | G93: Credit Card | H93: 10/20/2022 | I93: Anthony Lane | J93: Ohio | K93: Cleveland | L93: 2022-10
A94: B-26352 | B94: 9382 | C94: 1085 | D94: 3 | E94: Electronics | F94: Printers | G94: Debit Card | H94: 7/18/2023 | I94: Marcus Brown | J94: Illinois | K94: Chicago | L94: 2023-07
A95: B-26352 | B95: 9382 | C95: 1085 | D95: 3 | E95: Electronics | F95: Printers | G95: Debit Card | H95: 5/16/2022 | I95: Annette Pierce | J95: New York | K95: Rochester | L95: 2022-05
A96: B-25553 | B96: 9380 | C96: 414 | D96: 11 | E96: Electronics | F96: Phones | G96: UPI | H96: 5/30/2024 | I96: Karen Johnson | J96: New York | K96: Rochester | L96: 2024-05
A97: B-26740 | B97: 9369 | C97: 3297 | D97: 6 | E97: Electronics | F97: Printers | G97: Debit Card | H97: 9/27/2023 | I97: Stephanie Manning | J97: Florida | K97: Orlando | L97: 2023-09
A98: B-26740 | B98: 9369 | C98: 3297 | D98: 6 | E98: Electronics | F98: Printers | G98: Debit Card | H98: 1/30/2025 | I98: Logan Galloway | J98: New York | K98: New York City | L98: 2025-01
A99: B-26157 | B99: 9337 | C99: 554 | D99: 11 | E99: Office Supplies | F99: Pens | G99: COD | H99: 12/14/2023 | I99: Sierra Rios | J99: Florida | K99: Orlando | L99: 2023-12
... A106: B-25603 | B106: 9272 | C106: 1771 | D106: 19 | E106: Office Supplies | F106: Markers | G106: UPI | H106: 4/18/2020 | I106: Lauren Boyer | J106: Texas | K106: Dallas | L106: 2020-04
...

Sheet DASHBOARD
A1: SALES PERFORMANCE DASHBOARD 2020-2025
A3: COMPANY NAME: RETAIL PRO INDIA | E3: =UPPER("Category: Electronics | Furniture | Office Supplies") -> CATEGORY: ELECTRONICS | FURNITURE | OFFICE SUPPLIES | I3: STATES: 6 | L3: PERIOD: 2020-2025
A5: TOTAL REVENUE | D5: TOTAL PROFIT | G5: TOTAL ORDERS | J5: AVERAGE ORDER VALUE | M5: TOTAL QUANTITY
A8: =Analysis!B1 -> 6173150 | D8: =Analysis!B2 -> 1610697 | G8: =Analysis!B8 -> 1194 | J8: =Analysis!B7 -> 5170.1424 | M8: =Analysis!B3 -> 12745

Sheet Analysis
A1: TOTAL AMOUNT | B1: =SUM(sales_dataset!B:B) -> 6173150 | D1: COUNT
A2: TOTAL PROFIT | B2: =SUM(sales_dataset!C:C) -> 1610697 | D2: OFFICE SUPPLIES | E2: =COUNTIF(sales_dataset!E:E,"Office Supplies") -> 399
A3: TOTAL QUANTITY | B3: =SUM(sales_dataset!D:D) -> 12745 | D3: Furniture | E3: =COUNTIF(sales_dataset!E:E,"Furniture") -> 407
D4: Electronics | E4: =COUNTIF(sales_dataset!E:E,"Electronics") -> 388
A5: MAX AMOUNT | B5: =MAX(sales_dataset!B:B) -> 9992
A6: MIN AMOUNT | B6: =MIN(sales_dataset!B:B) -> 500
A7: AVERAGE AMOUNT | B7: =AVERAGE(sales_dataset!B:B) -> 5170.1424
A8: TOTAL ORDERS | B8: =COUNTA(sales_dataset!A2:A1195) -> 1194
A9: REVENUE PER CATEGORY
A10: Office Supplies | B10: =SUMIF(sales_dataset!E2:E1195, "Office Supplies",sales_dataset!B2:B1195) -> 2089510
A11: Furniture | B11: =SUMIF(sales_dataset!E:E,"Furniture",sales_dataset!B:B) -> 2029184
A12: Electronics | B12: =SUMIF(sales_dataset!E:E,"Electronics",sales_dataset!B:B) -> 2054456
A13: PROFITS PER CATEGORY
A14: Office Supplies | B14: =SUMIF(sales_dataset!E2:E1195, "Office Supplies",sales_dataset!C2:C1195) -> 551575
A15: Furniture | B15: =SUMIF(sales_dataset!E2:E1195, "Furniture",sales_dataset!C2:C1195) -> 540542
A16: Electronics | B16: =SUMIF(sales_dataset!E2:E1195, "Electronics",sales_dataset!C2:C1195) -> 518580
A17: COUNT PER PAYMENT MODE
A18: DEBIT CARD | B18: =COUNTIF(sales_dataset!G2:G1195,"Debit Card") -> 260
A19: CREDIT CARD | B19: =COUNTIF(sales_dataset!G2:G1195,"Credit Card") -> 258
A20: UPI | B20: =COUNTIF(sales_dataset!G2:G1195,"UPI") -> 252
A21: EMI | B21: =COUNTIF(sales_dataset!G2:G1195,"EMI") -> 218
A22: COD | B22: =COUNTIF(sales_dataset!G2:G1195,"COD") -> 206

Sheet LOOKUP
A1: CUSTOMER NAME | B1: STATE | C1: CITY | D1: PAYMENT MODE
A2: Patrick Williams | B2: =VLOOKUP(A2,sales_dataset!I:J,2,0) -> New York | C2: =VLOOKUP(A2,sales_dataset!I:K,3,0) -> Rochester | D2: =IFERROR(_xlfn.XLOOKUP(A2,sales_dataset!I:I,sales_dataset!G:G),"Not Found") -> Debit Card
A3: Susan Burke | B3: =VLOOKUP(A3,sales_dataset!I:J,2,0) -> Texas | C3: =VLOOKUP(A3,sales_dataset!I:K,3,0) -> Austin | D3: =IFERROR(_xlfn.XLOOKUP(A3,sales_dataset!I:I,sales_dataset!G:G),"Not Found") -> Debit Card | F3: =LEN(TRIM(A2))-LEN(A2) -> 0
A4: Brent Hernandez | B4: =VLOOKUP(A4,sales_dataset!I:J,2,0) -> New York | C4: =VLOOKUP(A4,sales_dataset!I:K,3,0) -> Rochester | D4: =IFERROR(_xlfn.XLOOKUP(A4,sales_dataset!I:I,sales_dataset!G:G),"Not Found") -> Debit Card | F4: =TRIM(A5) -> Tammy Anthony
A5: Tammy Anthony | B5: =VLOOKUP(A5,sales_dataset!I:J,2,0) -> Ohio | C5: =VLOOKUP(A5,sales_dataset!I:K,3,0) -> Cleveland | D5: =IFERROR(_xlfn.XLOOKUP(A5,sales_dataset!I:I,sales_dataset!G:G),"Not Found") -> Debit Card
A6: Cassandra Farley | B6: =VLOOKUP(A6,sales_dataset!I:J,2,0) -> Florida | C6: =VLOOKUP(A6,sales_dataset!I:K,3,0) -> Orlando | D6: =IFERROR(_xlfn.XLOOKUP(A6,sales_dataset!I:I,sales_dataset!G:G),"Not Found") -> Debit Card
A7: Jennifer Marshall | B7: =VLOOKUP(A7,sales_dataset!I:J,2,0) -> California | C7: =VLOOKUP(A7,sales_dataset!I:K,3,0) -> San Francisco | D7: =IFERROR(_xlfn.XLOOKUP(A7,sales_dataset!I:I,sales_dataset!G:G),"Not Found") -> COD
A8: Frank Garcia | B8: =VLOOKUP(A8,sales_dataset!I:J,2,0) -> New York | C8: =VLOOKUP(A8,sales_dataset!I:K,3,0) -> Buffalo | D8: =IFERROR(_xlfn.XLOOKUP(A8,sales_dataset!I:I,sales_dataset!G:G),"Not Found") -> COD
A9: Tanya Thomas MD | B9: =VLOOKUP(A9,sales_dataset!I:J,2,0) -> Texas | C9: =VLOOKUP(A9,sales_dataset!I:K,3,0) -> Dallas | D9: =IFERROR(_xlfn.XLOOKUP(A9,sales_dataset!I:I,sales_dataset!G:G),"Not Found") -> Debit Card
A10: Christopher Rogers | B10: =VLOOKUP(A10,sales_dataset!I:J,2,0) -> Illinois | C10: =VLOOKUP(A10,sales_dataset!I:K,3,0) -> Chicago | D10: =IFERROR(_xlfn.XLOOKUP(A10,sales_dataset!I:I,sales_dataset!G:G),"Not Found") -> EMI
A11: Kelly Smith | B11: =VLOOKUP(A11,sales_dataset!I:J,2,0) -> Ohio | C11: =VLOOKUP(A11,sales_dataset!I:K,3,0) -> Cleveland | D11: =IFERROR(_xlfn.XLOOKUP(A11,sales_dataset!I:I,sales_dataset!G:G),"Not Found") -> UPI
A12: Sabrina Hartman | B12: =VLOOKUP(A12,sales_dataset!I:J,2,0) -> Florida | C12: =VLOOKUP(A12,sales_dataset!I:K,3,0) -> Tampa | D12: =IFERROR(_xlfn.XLOOKUP(A12,sales_dataset!I:I,sales_dataset!G:G),"Not Found") -> UPI
A13: Jeffrey Weber | B13: =VLOOKUP(A13,sales_dataset!I:J,2,0) -> New York | C13: =VLOOKUP(A13,sales_dataset!I:K,3,0) -> Buffalo | D13: =IFERROR(_xlfn.XLOOKUP(A13,sales_dataset!I:I,sales_dataset!G:G),"Not Found") -> Credit Card
A14: Andrew Krueger | B14: =VLOOKUP(A14,sales_dataset!I:J,2,0) -> New York | C14: =VLOOKUP(A14,sales_dataset!I:K,3,0) -> Rochester | D14: =IFERROR(_xlfn.XLOOKUP(A14,sales_dataset!I:I,sales_dataset!G:G),"Not Found") -> Credit Card
A15: Albert Alexander Jr. | B15: =VLOOKUP(A15,sales_dataset!I:J,2,0) -> Ohio | C15: =VLOOKUP(A15,sales_dataset!I:K,3,0) -> Cleveland | D15: =IFERROR(_xlfn.XLOOKUP(A15,sales_dataset!I:I,sales_dataset!G:G),"Not Found") -> COD
A16: Teresa Perez | B16: =VLOOKUP(A16,sales_dataset!I:J,2,0) -> Texas | C16: =VLOOKUP(A16,sales_dataset!I:K,3,0) -> Austin | D16: =IFERROR(_xlfn.XLOOKUP(A16,sales_dataset!I:I,sales_dataset!G:G),"Not Found") -> COD
... A1195: Jennifer Chase | B1195: =VLOOKUP(A1195,sales_dataset!I:J,2,0) -> New York | C1195: =VLOOKUP(A1195,sales_dataset!I:K,3,0) -> Buffalo | D1195: =IFERROR(_xlfn.XLOOKUP(A1195,sales_dataset!I:I,sales_dataset!G:G),"Not Found") -> Debit Card
